{"name":"GeoTrust Primary Certification Authority - G2","sub":"CN=GeoTrust Primary Certification Authority - G2, OU=(c) 2007 GeoTrust Inc. - For authorized use only, O=GeoTrust Inc., C=US","exp":"1/18/2038 3:59:59 PM","iss":"CN=GeoTrust Primary Certification Authority - G2, OU=(c) 2007 GeoTrust Inc. - For authorized use only, O=GeoTrust Inc., C=US","children":[{"name":"","sub":"C=US, O=Apple Inc., OU=Certification Authority, CN=Apple IST CA 8 - G1","exp":"6/8/2031 4:59:59 PM","children":[{"name":"","sub":"C=US, S=California, O=Apple Inc., OU=management:idms.group.665035, CN=icloud.com","exp":"4/9/2021 2:25:35 PM","ser":"3bb47895b26632d3ae054792eeda38ba","thumb":"7a26495bb5f4ec7d9f89d6d1bc1524c72bc8430a"}],"ser":"13522ebfc1dd5ce11ef27640751fe7df","thumb":"f2f440ab16d7cae39e73270e97266dff15606ec0"}],"ser":"3cb2f4480a00e2feeb243b5e603ec36b","thumb":"8d1784d537f3037dec70fe578b519a99e610d7b0"}